LICENSE
README.md
setup.py
mediaTools/__init__.py
mediaTools/image.py
mediaTools/video.py
simply_media_tools.egg-info/PKG-INFO
simply_media_tools.egg-info/SOURCES.txt
simply_media_tools.egg-info/dependency_links.txt
simply_media_tools.egg-info/requires.txt
simply_media_tools.egg-info/top_level.txt