Metadata-Version: 2.1
Name: simply-media-tools
Version: 0.0.1
Summary: Simply do something with your media file
Home-page: https://github.com/Arsybai/simply-media-tools
Author: Arsybai
Author-email: me@arsybai.com
License: MIT
Keywords: mediaTools,quicktools,background remover,video trimmer,profile picture maker,video cropper,compress image,video trimmer
License-File: LICENSE
